mutable/__init__.py
mutable/callbacks.py
mutable/openai.py
mutable/payment_refactor.py
mutable/helpers/__init__.py
mutable/helpers/outcome_simulation.py
mutable_dev-0.1.7.7.dist-info/METADATA
mutable_dev-0.1.7.7.dist-info/WHEEL
mutable_dev-0.1.7.7.dist-info/top_level.txt
mutable_dev-0.1.7.7.dist-info/RECORD
