Metadata-Version: 2.1
Name: mutable-dev
Version: 0.1.7.7
Summary: Success-based pricing SDK for LLM-based applications
Home-page: UNKNOWN
Author: Mutable
Author-email: chase@mutability.ai
License: UNKNOWN
Platform: UNKNOWN
Classifier: Programming Language :: Python :: 3
Classifier: License :: OSI Approved :: MIT License
Classifier: Operating System :: OS Independent
Requires-Python: >=3.11
